invenio_upgrader/__init__.py
invenio_upgrader/api.py
invenio_upgrader/checks.py
invenio_upgrader/commands.py
invenio_upgrader/engine.py
invenio_upgrader/logging.py
invenio_upgrader/manage.py
invenio_upgrader/models.py
invenio_upgrader/operations.py
invenio_upgrader/version.py
invenio_upgrader/translations/invenio.pot
invenio_upgrader/translations/de/LC_MESSAGES/messages.mo
invenio_upgrader/translations/de/LC_MESSAGES/messages.po
invenio_upgrader/translations/es/LC_MESSAGES/messages.mo
invenio_upgrader/translations/es/LC_MESSAGES/messages.po
invenio_upgrader/translations/fr/LC_MESSAGES/messages.mo
invenio_upgrader/translations/fr/LC_MESSAGES/messages.po
invenio_upgrader/translations/it/LC_MESSAGES/messages.mo
invenio_upgrader/translations/it/LC_MESSAGES/messages.po
invenio_upgrader/upgrades/__init__.py
invenio_upgrader/upgrades/invenio_2015_07_14_innodb.py
invenio_upgrader/upgrades/invenio_upgrader_2015_09_23_legacy_removal.py
invenio_upgrader-0.2.0.dist-info/top_level.txt
invenio_upgrader-0.2.0.dist-info/METADATA
invenio_upgrader-0.2.0.dist-info/DESCRIPTION.rst
invenio_upgrader-0.2.0.dist-info/metadata.json
invenio_upgrader-0.2.0.dist-info/WHEEL
invenio_upgrader-0.2.0.dist-info/RECORD
