Metadata-Version: 2.0
Name: invenio-upgrader
Version: 0.2.0
Summary: Upgrader engine for Invenio modules.
Home-page: https://github.com/inveniosoftware/invenio-upgrader
Author: CERN
Author-email: info@invenio-software.org
License: GPLv2
Keywords: invenio upgrade alembic
Platform: any
Classifier: Environment :: Web Environment
Classifier: Intended Audience :: Developers
Classifier: License :: OSI Approved :: GNU General Public License v2 (GPLv2)
Classifier: Operating System :: OS Independent
Classifier: Programming Language :: Python
Classifier: Topic :: Internet :: WWW/HTTP :: Dynamic Content
Classifier: Topic :: Software Development :: Libraries :: Python Modules
Classifier: Programming Language :: Python :: 2
Classifier: Programming Language :: Python :: 2.7
Classifier: Development Status :: 1 - Planning
Requires-Dist: alembic (>=0.7,<0.8)
Requires-Dist: Flask (>=0.10.1)
Requires-Dist: six (>=1.7.2)
Requires-Dist: invenio-base (>=0.3.0)
Requires-Dist: invenio-ext (>=0.2.1)
Requires-Dist: invenio-utils (>=0.1.1)
Provides-Extra: docs
Requires-Dist: Sphinx (>=1.3); extra == 'docs'
Requires-Dist: sphinx-rtd-theme (>=0.1.7); extra == 'docs'
Provides-Extra: tests
Requires-Dist: unittest2 (>=1.1.0); extra == 'tests'
Requires-Dist: Flask-Testing (>=0.4.1); extra == 'tests'
Requires-Dist: pytest (>=2.8.0); extra == 'tests'
Requires-Dist: pytest-cov (>=2.1.0); extra == 'tests'
Requires-Dist: pytest-pep8 (>=1.0.6); extra == 'tests'
Requires-Dist: coverage (>=4.0.0); extra == 'tests'
Requires-Dist: invenio-testing (>=0.1.1); extra == 'tests'
